foliohouse/__init__.py
foliohouse/load_dataset.py
foliohouse-0.0.1.dist-info/METADATA
foliohouse-0.0.1.dist-info/WHEEL
foliohouse-0.0.1.dist-info/top_level.txt
foliohouse-0.0.1.dist-info/RECORD
